tealprint/__init__.py
tealprint/tealconfig.py
tealprint/teallevel.py
tealprint/tealprint.py
tealprint/tealprint_test.py
tealprint/tealprintbuffer.py
tealprint/tealprintbuffer_test.py
tealprint-0.3.0.dist-info/LICENSE
tealprint-0.3.0.dist-info/METADATA
tealprint-0.3.0.dist-info/WHEEL
tealprint-0.3.0.dist-info/top_level.txt
tealprint-0.3.0.dist-info/RECORD
