Metadata-Version: 2.1
Name: tealprint
Version: 0.3.0
Summary: Prints messages to the console
Home-page: https://github.com/Senth/tealprint
Author: Matteus Magnusson
Author-email: senth.wallace@gmail.com
License: MIT
Platform: UNKNOWN
Classifier: Development Status :: 2 - Pre-Alpha
Classifier: Topic :: Software Development :: Libraries
Classifier: License :: OSI Approved :: MIT License
Classifier: Programming Language :: Python :: 3.8
Classifier: Programming Language :: Python :: 3.9
Classifier: Programming Language :: Python :: 3.10
Requires-Python: >=3.8
License-File: LICENSE
Requires-Dist: colored
